.DS_Store
demyst/.DS_Store
demyst/report/.DS_Store
demyst/report/__init__.py
demyst/report/corr.py
demyst/report/report.py
demyst/report/files/cover-style.css
demyst/report/files/cover.html
demyst/report/files/demyst_logo_gray.svg
demyst/report/files/footer.html
demyst/report/files/header.html
demyst/report/files/style.css
demyst_report-0.9.0.dist-info/METADATA
demyst_report-0.9.0.dist-info/WHEEL
demyst_report-0.9.0.dist-info/top_level.txt
demyst_report-0.9.0.dist-info/RECORD
