Metadata-Version: 2.1
Name: demyst-report
Version: 0.9.0
Author: Demyst Data
Author-email: info@demystdata.com
Requires-Dist: demyst-analytics (>=0.9.0)
Requires-Dist: matplotlib (==3.1.2)
Requires-Dist: scipy (==1.5.4)
Requires-Dist: seaborn (==0.10.0)
